frenztoolkit/__init__.py
frenztoolkit/reader.cpython-39-darwin.so
frenztoolkit/scanner.cpython-39-darwin.so
frenztoolkit/streamer.cpython-39-darwin.so
frenztoolkit/utilsthon_utils.cpython-39-darwin.so
frenztoolkit/RawSignal/BLEBleak.cpython-39-darwin.so
frenztoolkit/RawSignal/BinaryLoader2.cpython-39-darwin.so
frenztoolkit/RawSignal/BufferData.cpython-39-darwin.so
frenztoolkit/RawSignal/DataLoader2.cpython-39-darwin.so
frenztoolkit/RawSignal/Experiment.cpython-39-darwin.so
frenztoolkit/RawSignal/OfflineReplay.cpython-39-darwin.so
frenztoolkit/RawSignal/Preprocessing.cpython-39-darwin.so
frenztoolkit/RawSignal/Windowing.cpython-39-darwin.so
frenztoolkit/RawSignal/__init__.py
frenztoolkit/RawSignal/rawsignal.cpython-39-darwin.so
frenztoolkit/STATE/__init__.py
frenztoolkit/STATE/state.cpython-39-darwin.so
frenztoolkit/STATE/algorithms/blink_detection.cpython-39-darwin.so
frenztoolkit/STATE/algorithms/emg_event_detection.cpython-39-darwin.so
frenztoolkit/STATE/algorithms/feature_extractor.cpython-39-darwin.so
frenztoolkit/STATE/algorithms/focus.cpython-39-darwin.so
frenztoolkit/STATE/algorithms/focus_2.cpython-39-darwin.so
frenztoolkit/STATE/algorithms/gaze_3.cpython-39-darwin.so
frenztoolkit/STATE/algorithms/gaze_detection.cpython-39-darwin.so
frenztoolkit/STATE/algorithms/gesture.cpython-39-darwin.so
frenztoolkit/STATE/algorithms/gesture_2.cpython-39-darwin.so
frenztoolkit/STATE/algorithms/poas.cpython-39-darwin.so
frenztoolkit/STATE/algorithms/posture.cpython-39-darwin.so
frenztoolkit/STATE/algorithms/posture_2.cpython-39-darwin.so
frenztoolkit/STATE/algorithms/respiratory_rate.cpython-39-darwin.so
frenztoolkit/STATE/algorithms/sleep_helper_function.cpython-39-darwin.so
frenztoolkit/STATE/algorithms/sleep_pack.cpython-39-darwin.so
frenztoolkit/STATE/algorithms/sleep_poas.cpython-39-darwin.so
frenztoolkit/STATE/algorithms/smooth_sleep_stage.cpython-39-darwin.so
frenztoolkit/STATE/algorithms/model_files/eyes_condition.encrypted
frenztoolkit-0.3.2.dist-info/licenses/LICENSE
frenztoolkit-0.3.2.dist-info/METADATA
frenztoolkit-0.3.2.dist-info/WHEEL
frenztoolkit-0.3.2.dist-info/top_level.txt
frenztoolkit-0.3.2.dist-info/RECORD
