Metadata-Version: 2.4
Name: frenztoolkit
Version: 0.3.2
Summary: A toolkit for processing and analyzing physiological signals
Home-page: https://github.com/earable/frenztoolkit
Author: Frenz Team
Author-email: Frenz Team <ml1@earable.ai>
License: MIT
Requires-Python: >=3.8
License-File: LICENSE
Requires-Dist: numpy==1.26.4
Requires-Dist: pandas>=2.0
Requires-Dist: requests>=2.31.0
Requires-Dist: python-dotenv>=1.0.0
Requires-Dist: bleak==1.0.1
Requires-Dist: scipy>=1.11.0
Requires-Dist: pyedflib>=0.1.20
Requires-Dist: matplotlib>=3.5.0
Requires-Dist: statsmodels>=0.14.0
Requires-Dist: seaborn>=0.12.0
Requires-Dist: tensorflow==2.16.2
Requires-Dist: antropy>=0.1.6
Requires-Dist: cryptography
Requires-Dist: scikit-learn
Requires-Dist: tqdm
Requires-Dist: scikit-image
Requires-Dist: cassandra-driver
Requires-Dist: psutil
Requires-Dist: boto3
Requires-Dist: tzlocal
Requires-Dist: pytz
Requires-Dist: pyobjc-core==11.1
Requires-Dist: pyobjc-framework-Cocoa==11.1
Provides-Extra: dev
Requires-Dist: build>=0.10.0; extra == "dev"
Requires-Dist: twine>=4.0.2; extra == "dev"
Requires-Dist: pytest>=7.0.0; extra == "dev"
Requires-Dist: setuptools>=61.0; extra == "dev"
Requires-Dist: wheel>=0.40.0; extra == "dev"
Dynamic: author
Dynamic: home-page
Dynamic: license-file
Dynamic: requires-python
